carrot-rcc
carrot_rcc.py
carrot_rcc-0.8.3.dist-info/LICENSE
carrot_rcc-0.8.3.dist-info/METADATA
carrot_rcc-0.8.3.dist-info/WHEEL
carrot_rcc-0.8.3.dist-info/entry_points.txt
carrot_rcc-0.8.3.dist-info/RECORD
