Metadata-Version: 2.1
Name: carrot-rcc
Version: 0.8.3
Summary: Camunda external task Robot Framework RCC client
Home-page: https://github.com/datakurre/carrot-rcc
License: Apache-2.0
Author: Asko Soukka
Author-email: asko.soukka@iki.fi
Requires-Python: >=3.8,<4.0
Classifier: License :: OSI Approved :: Apache Software License
Classifier: Programming Language :: Python :: 3
Classifier: Programming Language :: Python :: 3.8
Classifier: Programming Language :: Python :: 3.9
Classifier: Programming Language :: Python :: 3.10
Classifier: Programming Language :: Python :: 3.11
